{
  "chapter_id": "VI",
  "title": "Les foncteurs \\(\\operatorname{Ext}^{\\bullet }_Z(X;F, G)\\) et \\(\\mathop{\\underline{\\mathrm{Ext}}}\\nolimits ^{\\bullet }_Z(F, G)\\)",
  "pages": [
    {
      "id": "VI",
      "title": "Les foncteurs \\(\\operatorname{Ext}^{\\bullet }_Z(X;F, G)\\) et \\(\\mathop{\\underline{\\mathrm{Ext}}}\\nolimits ^{\\bullet }_Z(F, G)\\)",
      "html": "",
      "blocks": [],
      "footnotes": [],
      "bibliography": []
    },
    {
      "id": "VI-1",
      "title": "Généralités",
      "html": "",
      "blocks": [],
      "footnotes": [],
      "bibliography": []
    },
    {
      "id": "VI-2",
      "title": "Applications aux faisceaux quasi-cohérents sur les préschémas",
      "html": "",
      "blocks": [],
      "footnotes": [],
      "bibliography": []
    },
    {
      "id": "sect0003",
      "title": "Bibliographie",
      "html": "",
      "blocks": [],
      "footnotes": [],
      "bibliography": []
    }
  ]
}